charybdis/__init__.py
charybdis/charybdis.py
charybdis/py.typed
charybdis-2.0.0.dist-info/LICENSE
charybdis-2.0.0.dist-info/WHEEL
charybdis-2.0.0.dist-info/METADATA
charybdis-2.0.0.dist-info/RECORD
