Metadata-Version: 2.1
Name: charybdis
Version: 2.0.0
Summary: Tiny Hi-Rez API wrapper
Requires-Python: >=3.10
Requires-Dist: httpx
Project-URL: Source Code, https://github.com/NAZADOTH/charybdis
